tmdb/__init__.py
tmdb/four/__init__.py
tmdb/four/account.py
tmdb/four/auth.py
tmdb/four/base.py
tmdb/four/list.py
tmdb/three/__init__.py
tmdb/three/account.py
tmdb/three/authentication.py
tmdb/three/base.py
tmdb/three/certifications.py
tmdb/three/changes.py
tmdb/three/collections.py
tmdb/three/companies.py
tmdb/three/configuration.py
tmdb/three/credits.py
tmdb/three/discover.py
tmdb/three/find.py
tmdb/three/genres.py
tmdb/three/guest_sessions.py
tmdb/three/keywords.py
tmdb/three/lists.py
tmdb/three/movies.py
tmdb/three/networks.py
tmdb/three/people.py
tmdb/three/reviews.py
tmdb/three/search.py
tmdb/three/trending.py
tmdb/three/tv.py
tmdb/three/tv_episode_groups.py
tmdb/three/tv_episodes.py
tmdb/three/tv_seasons.py
tmdb/three/watch_providers.py
ezapi_tmdb-0.8.4.dist-info/LICENSE
ezapi_tmdb-0.8.4.dist-info/METADATA
ezapi_tmdb-0.8.4.dist-info/WHEEL
ezapi_tmdb-0.8.4.dist-info/top_level.txt
ezapi_tmdb-0.8.4.dist-info/RECORD
