Metadata-Version: 2.1
Name: ezapi-tmdb
Version: 0.8.4
Summary: A Python wrapper for TMDb API
Author-email: Zeheng Li <imzehengl@gmail.com>
Maintainer-email: Zeheng Li <imzehengl@gmail.com>
Project-URL: repository, https://github.com/zehengl/ezapi-tmdb
Project-URL: homepage, https://zehengl.github.io/ezapi-tmdb/
Keywords: TMDb
Classifier: Programming Language :: Python :: 3
Classifier: License :: OSI Approved :: MIT License
Classifier: Operating System :: OS Independent
Requires-Python: >=3.8
License-File: LICENSE
Requires-Dist: requests ==2.31.0
Requires-Dist: wrapt ==1.16.0
